sdl_webui_lite/__init__.py
sdl_webui_lite/app.py
sdl_webui_lite/static/favicon.ico
sdl_webui_lite/static/logo.png
sdl_webui_lite/static/page_screenshot.png
sdl_webui_lite/static/style.css
sdl_webui_lite/templates/base.html
sdl_webui_lite/templates/experiment.html
sdl_webui_lite/templates/home.html
sdl_webui_lite/utils/__init__.py
sdl_webui_lite/utils/scheduler.py
sdl_webui_lite/utils/utils.py
sdl_webui_lite-0.1.2.dist-info/LICENSE
sdl_webui_lite-0.1.2.dist-info/METADATA
sdl_webui_lite-0.1.2.dist-info/WHEEL
sdl_webui_lite-0.1.2.dist-info/top_level.txt
sdl_webui_lite-0.1.2.dist-info/RECORD
