Metadata-Version: 2.1
Name: sdl-webui-lite
Version: 0.1.2
Summary: This web UI aims to ease up the control of any Python-based SDLs by displaying functions and their parameters dynamically.
Home-page: https://gitlab.com/heingroup/sdl_webui_lite
Author: Ivory Zhang
Author-email: ivoryzhang@chem.ubc.ca
License: MIT
License-File: LICENSE
Requires-Dist: Flask-SocketIO
